
{
  "id": "author-1",
  "name": "Анна Миронова",
  "description": "Привет! Я Анна, автор этого блога о повседневных радостях, уютном доме и вкусной еде. Люблю готовить, путешествовать, исследовать новые кафе и делиться своими открытиями.",
  "longDescription": "Уже более пяти лет я веду этот блог, в котором делюсь рецептами, идеями для дома, личными мыслями и впечатлениями от посещения различных кафе и ресторанов. Моя цель — показать, как находить радость в мелочах и создавать уют вокруг себя.\n\nПо образованию я дизайнер интерьеров, но настоящая страсть — это кулинария и писательство. В свободное время люблю читать, заниматься йогой и путешествовать по маленьким городкам России.\n\nБлагодарю вас за то, что читаете мой блог и делитесь своими мыслями в комментариях!",
  "avatar": "https://images.unsplash.com/photo-1544005313-94ddf0286df2?auto=format&fit=crop&q=80&w=988",
  "socialNetworks": [
    {
      "id": "social-1",
      "name": "Instagram",
      "url": "https://instagram.com/anna_mironova"
    },
    {
      "id": "social-2",
      "name": "Telegram",
      "url": "https://t.me/anna_mironova_blog"
    },
    {
      "id": "social-3",
      "name": "Pinterest",
      "url": "https://pinterest.com/anna_mironova"
    },
    {
      "id": "social-4",
      "name": "Youtube",
      "url": "https://youtube.com/c/anna_mironova"
    }
  ]
}
